[
    {
        "id":"1",
        "image":"blog-18.jpg",
        "job":"Marketing",
        "name":"Robert Forex",
        "date":"21 Jan, 2023",
        "title":"Learn Python – Interactive Free Tutorials",
        "text":"Do you want to move on next step? Choose your most popular"
    },
    {
        "id":"2",
        "image":"blog-19.jpg",
        "job":"Designer",
        "name":"Leonardo",
        "date":"25 Jan, 2023",
        "title":"Learn Python – Interactive Free Tutorials",
        "text":"Do you want to move on next step? Choose your most popular"
    },
    {
        "id":"3",
        "image":"blog-20.jpg",
        "job":"Developer",
        "name":"Madison",
        "date":"19 Jan, 2023",
        "title":"Learn Python – Interactive Free Tutorials",
        "text":"Do you want to move on next step? Choose your most popular"
    },
    {
        "id":"1",
        "image":"blog-18.jpg",
        "job":"Designer",
        "name":"Alexander",
        "date":"20 Jan, 2023",
        "title":"Learn Python – Interactive Free Tutorials",
        "text":"Do you want to move on next step? Choose your most popular"
    }
]