[
    {   
        "id": 1,
        "sno": "1",
        "image": "user.jpg",
        "category": "Painting",
        "date": "3 Apr 2020"
    },
    {
        "id": 2,
        "sno": "2",
        "image": "user1.jpg",
        "category": "Interior",
        "date": "3 Apr 2020"
    },
    {
        "id": 3,
        "sno": "3",
        "image": "user2.jpg",
        "category": "Electrical",
        "date": "3 Apr 2020"
    },
    {
        "id": 4,
        "sno": "4",
        "image": "user3.jpg",
        "category": "Construction",
        "date": "3 Apr 2020"
    },
    {
        "id": 5,
        "sno": "5",
        "image": "user4.jpg",
        "category": "Computer",
        "date": "3 Apr 2020"
    }
]